adcat/__init__.py
adcat/bintree.py
adcat/huffman.py
adcat/linkedlist.py
adcat-0.0.1.dist-info/LICENSE
adcat-0.0.1.dist-info/METADATA
adcat-0.0.1.dist-info/WHEEL
adcat-0.0.1.dist-info/top_level.txt
adcat-0.0.1.dist-info/RECORD
