Metadata-Version: 2.1
Name: adcat
Version: 0.0.1
Summary: adcat is Algorithm and DataStructure toolbox write in python
Home-page: https://github.com/istommao/adcat
Author: silence
Author-email: istommao@gmail.com
License: UNKNOWN
Keywords: adcat is Algorithm and DataStructure toolbox write in python
Platform: UNKNOWN
